piet/__init__.py
piet/carbon.py
piet/mondrian.py
piet-0.1.0.dist-info/METADATA
piet-0.1.0.dist-info/WHEEL
piet-0.1.0.dist-info/RECORD
